fh_tailwind/__init__.py
fh_tailwind/_modidx.py
fh_tailwind/core.py
fh_tailwind-0.0.2.dist-info/LICENSE
fh_tailwind-0.0.2.dist-info/METADATA
fh_tailwind-0.0.2.dist-info/WHEEL
fh_tailwind-0.0.2.dist-info/entry_points.txt
fh_tailwind-0.0.2.dist-info/top_level.txt
fh_tailwind-0.0.2.dist-info/RECORD
