Metadata-Version: 2.1
Name: fh_tailwind
Version: 0.0.2
Summary: Tool to use  Tailwind CSS and Daisyui in your FastHTML projects.
Home-page: https://github.com/fbereilh/fh_tailwind
Author: Felipe
Author-email: fbereilh@thero.com
License: MIT License
Keywords: nbdev jupyter notebook python
Classifier: Development Status :: 4 - Beta
Classifier: Intended Audience :: Developers
Classifier: Natural Language :: English
Classifier: Programming Language :: Python :: 3.7
Classifier: Programming Language :: Python :: 3.8
Classifier: Programming Language :: Python :: 3.9
Classifier: Programming Language :: Python :: 3.10
Classifier: Programming Language :: Python :: 3.11
Classifier: Programming Language :: Python :: 3.12
Classifier: License :: OSI Approved :: MIT License
Requires-Python: >=3.7
License-File: LICENSE
Requires-Dist: python-fasthtml
Provides-Extra: dev
